{"Items":[
	{"ID":"1.0","type":"gold","resIcon":"shop/shopItem001","refresh":"day","price":"20.0","platformId":"","productContent":"[{\"id\":2, \"amount\":1}, {\"id\":2, \"amount\":1}]","beginAt":"","endAt":"","limitAmount":"-1.0","rate":"100.0"},
	{"ID":"2.0","type":"diamond","resIcon":"shop/shopItem002","refresh":"week","price":"100.0","platformId":"","productContent":"[{\"id\":2, \"amount\":1}, {\"id\":2, \"amount\":1}]","beginAt":"","endAt":"","limitAmount":"-1.0","rate":"100.0"},
	{"ID":"3.0","type":"diamond","resIcon":"shop/shopItem002","refresh":"month","price":"600.0","platformId":"","productContent":"[{\"id\":2, \"amount\":1}, {\"id\":2, \"amount\":1}]","beginAt":"","endAt":"","limitAmount":"-1.0","rate":"100.0"},
	{"ID":"4.0","type":"pay","resIcon":"shop/shopItem003","refresh":"none","price":"328.0","platformId":"co.jp.crazyfish.item001","productContent":"[{\"id\":3, \"amount\":328}]","beginAt":"","endAt":"","limitAmount":"-1.0","rate":"100.0"},
	{"ID":"5.0","type":"gold","resIcon":"shop/shopItem001","refresh":"day","price":"30.0","platformId":"","productContent":"[{\"id\":2, \"amount\":1}, {\"id\":2, \"amount\":1}]","beginAt":"","endAt":"","limitAmount":"-1.0","rate":"50.0"},
	{"ID":"6.0","type":"gold","resIcon":"shop/shopItem001","refresh":"day","price":"40.0","platformId":"","productContent":"[{\"id\":2, \"amount\":1}, {\"id\":2, \"amount\":1}]","beginAt":"","endAt":"","limitAmount":"-1.0","rate":"50.0"},
	{"ID":"7.0","type":"gold","resIcon":"shop/shopItem001","refresh":"none","price":"50.0","platformId":"","productContent":"[{\"id\":2, \"amount\":1}, {\"id\":2, \"amount\":1}]","beginAt":"","endAt":"","limitAmount":"-1.0","rate":"100.0"},
	{"ID":"8.0","type":"gold","resIcon":"shop/shopItem001","refresh":"none","price":"60.0","platformId":"","productContent":"[{\"id\":2, \"amount\":1}, {\"id\":2, \"amount\":1}]","beginAt":"","endAt":"","limitAmount":"-1.0","rate":"100.0"}
]}